Metadata-Version: 1.1
Name: ebclient.py
Version: 0.1.22
Summary: EnigmaBridge Python Client
Home-page: https://github.com/EnigmaBridge/client.py
Author: Enigma Bridge
Author-email: info@enigmabridge.com
License: MIT License
